README.rst
setup.cfg
setup.py
src/e_lti.egg-info/PKG-INFO
src/e_lti.egg-info/SOURCES.txt
src/e_lti.egg-info/dependency_links.txt
src/e_lti.egg-info/requires.txt
src/e_lti.egg-info/top_level.txt
src/e_lti.egg-info/zip-safe
src/elti/__init__.py
src/elti/contentitem_response.py
src/elti/launch_params.py
src/elti/outcome_request.py
src/elti/outcome_response.py
src/elti/tool_base.py
src/elti/tool_config.py
src/elti/tool_consumer.py
src/elti/tool_outbound.py
src/elti/tool_provider.py
src/elti/tool_proxy.py
src/elti/utils.py
src/elti/contrib/__init__.py
src/elti/contrib/django/__init__.py
src/elti/contrib/django/django_tool_provider.py
src/elti/contrib/flask/__init__.py
src/elti/contrib/flask/flask_tool_provider.py