Metadata-Version: 1.1
Name: e-lti
Version: 0.9.5
Summary: A python library for building and/or consuming LTI apps. Forked from https://github.com/pylti/lti
Home-page: https://github.com/CaptainAchilles/lti
Author: Nicholas Achilles
Author-email: nich@nich.tech
License: MIT License
Keywords: lti
Platform: UNKNOWN
Classifier: Programming Language :: Python :: 2
Classifier: Programming Language :: Python :: 2.7
Classifier: Programming Language :: Python :: 3
Classifier: Programming Language :: Python :: 3.5
Classifier: Programming Language :: Python :: 3.6
